wise_banking_api_client/LICENSE
wise_banking_api_client/__init__.py
wise_banking_api_client/__main__.py
wise_banking_api_client/_version.py
wise_banking_api_client/account_details.py
wise_banking_api_client/balance_statements.py
wise_banking_api_client/balances.py
wise_banking_api_client/base.py
wise_banking_api_client/borderless_account.py
wise_banking_api_client/cli.py
wise_banking_api_client/client.py
wise_banking_api_client/currency.py
wise_banking_api_client/default.pem
wise_banking_api_client/deprecation.py
wise_banking_api_client/endpoint.py
wise_banking_api_client/exceptions.py
wise_banking_api_client/keys.py
wise_banking_api_client/multi_currency_account.py
wise_banking_api_client/profile.py
wise_banking_api_client/quote.py
wise_banking_api_client/recipient_account.py
wise_banking_api_client/sandbox_simulation.py
wise_banking_api_client/signing.py
wise_banking_api_client/subscription.py
wise_banking_api_client/transfer.py
wise_banking_api_client/user.py
wise_banking_api_client/version.py
wise_banking_api_client/webhooks.py
wise_banking_api_client/model/__init__.py
wise_banking_api_client/model/account.py
wise_banking_api_client/model/account_requirement_type.py
wise_banking_api_client/model/annotations.py
wise_banking_api_client/model/base.py
wise_banking_api_client/model/country.py
wise_banking_api_client/model/country_codes.py
wise_banking_api_client/model/currency.py
wise_banking_api_client/model/enum.py
wise_banking_api_client/model/error.py
wise_banking_api_client/model/legal_type.py
wise_banking_api_client/model/payment.py
wise_banking_api_client/model/profile.py
wise_banking_api_client/model/quote.py
wise_banking_api_client/model/requirements.py
wise_banking_api_client/model/timestamp.py
wise_banking_api_client/model/transfer.py
wise_banking_api_client/model/uuid.py
wise_banking_api_client/model/recipient/__init__.py
wise_banking_api_client/model/recipient/__main__.py
wise_banking_api_client/model/recipient/address.py
wise_banking_api_client-0.0.3.dist-info/METADATA
wise_banking_api_client-0.0.3.dist-info/WHEEL
wise_banking_api_client-0.0.3.dist-info/entry_points.txt
wise_banking_api_client-0.0.3.dist-info/licenses/LICENSE
wise_banking_api_client-0.0.3.dist-info/RECORD
