Metadata-Version: 2.4
Name: wise-banking-api-client
Version: 0.0.3
Summary: Typed Python client library for the API of the bank Wise
Project-URL: Repository, https://github.com/foss-fund/wise-banking-api-client
Project-URL: source_archive, https://github.com/foss-fund/wise-banking-api-client/archive/3790f8d099967c8139ab12a9dd87507d947feeec.zip
Project-URL: Issues, https://github.com/foss-fund/wise-banking-api-client/issues
Author-email: James Addison <jay@jp-hosting.net>, Nicco Kunzmann <niccokunzmann@rambler.ru>
Maintainer-email: Nicco Kunzmann <niccokunzmann@rambler.ru>
License-Expression: AGPL-3.0
License-File: LICENSE
Keywords: balance,payments,transfer,wise
Classifier: Development Status :: 3 - Alpha
Classifier: Intended Audience :: Developers
Classifier: Intended Audience :: Financial and Insurance Industry
Classifier: License :: OSI Approved :: GNU Affero General Public License v3
Classifier: Operating System :: OS Independent
Classifier: Programming Language :: Python :: 3.12
Classifier: Programming Language :: Python :: 3.13
Classifier: Topic :: Internet
Classifier: Topic :: Office/Business :: Financial
Classifier: Topic :: Office/Business :: Financial :: Accounting
Classifier: Topic :: Office/Business :: Financial :: Investment
Classifier: Topic :: Office/Business :: Financial :: Point-Of-Sale
Classifier: Topic :: Security :: Cryptography
Classifier: Typing :: Typed
Requires-Python: ~=3.12
Requires-Dist: apiron>=8.0.0
Requires-Dist: cryptography>=44.0.0
Requires-Dist: munch>=4.0.0
Requires-Dist: pydantic>=2.10.4
Provides-Extra: cli
Requires-Dist: click>=8.1.8; extra == 'cli'
Provides-Extra: dev
Requires-Dist: black>=24.4.0; extra == 'dev'
Requires-Dist: munch-stubs>=0.1.2; extra == 'dev'
Requires-Dist: pytest-order>=1.3.0; extra == 'dev'
Requires-Dist: pytest>=8.1.1; extra == 'dev'
Requires-Dist: responses>=0.25.0; extra == 'dev'
Requires-Dist: types-cryptography>=3.3.23.2; extra == 'dev'
